{
  "lastUpdated": "2026-02-22T00:32:09.992Z",
  "nextUpdate": "2025-03-02T03:00:00Z",
  "dataSource": "Real-time scraped from gallery websites",
  "stats": {
    "totalGalleries": 0,
    "totalExhibitions": 0,
    "scrapedGalleries": 0
  },
  "cities": {
    "New York": {
      "galleryCount": 0,
      "exhibitionCount": 0,
      "galleries": [],
      "exhibitions": []
    },
    "Beijing": {
      "galleryCount": 0,
      "exhibitionCount": 0,
      "galleries": [],
      "exhibitions": []
    },
    "Shanghai": {
      "galleryCount": 0,
      "exhibitionCount": 0,
      "galleries": [],
      "exhibitions": []
    },
    "Hong Kong": {
      "galleryCount": 0,
      "exhibitionCount": 0,
      "galleries": [],
      "exhibitions": []
    }
  }
}